{"is_source_file": true, "format": "Java", "description": "This class serves as the entry point for the Todo backend application built with Spring Boot. It sets up the application configuration and API documentation metadata using OpenAPI annotations.", "external_files": ["org.springframework.boot.SpringApplication", "org.springframework.boot.autoconfigure.SpringBootApplication", "io.swagger.v3.oas.annotations.OpenAPIDefinition", "io.swagger.v3.oas.annotations.info.Info"], "external_methods": ["SpringApplication.run"], "published": ["com.example.todobackend.TodoBackendApplication"], "classes": [{"name": "TodoBackendApplication", "description": "Main application class annotated with @SpringBootApplication and OpenAPIDefinition, responsible for bootstrapping the Spring Boot application and providing API documentation metadata."}], "methods": [{"name": "main", "description": "Application entry point that launches the Spring Boot application using SpringApplication.run."}], "calls": ["SpringApplication.run"], "search-terms": ["Spring Boot application", "main class", "OpenAPI documentation", "Todo backend API", "Application entry point"], "state": 2, "file_id": 2, "knowledge_revision": 13, "git_revision": "3535cce73fcb5ea6d3f91731970dce309d2b6417", "revision_history": [{"10": "3535cce73fcb5ea6d3f91731970dce309d2b6417"}, {"13": "3535cce73fcb5ea6d3f91731970dce309d2b6417"}], "hash": "704467947f1057c0b1a5a960242cd847", "format-version": 4, "code-base-name": "todo_backend", "filename": "todo_backend/src/main/java/com/example/demo/todobackendApplication.java"}